ASnake/ASnake.py
ASnake/__init__.py
ASnake/__main__.py
ASnake/data/ASnakeAlias.bat
ASnake/data/megaTest.asnake
ASnake/data/setAlias.asnake
asnake-0.13.43.dist-info/licenses/LICENSE.txt
asnake-0.13.43.dist-info/METADATA
asnake-0.13.43.dist-info/WHEEL
asnake-0.13.43.dist-info/entry_points.txt
asnake-0.13.43.dist-info/top_level.txt
asnake-0.13.43.dist-info/RECORD
