Metadata-Version: 2.4
Name: ASnake
Version: 0.13.43
Summary: Python optimizing compiler for the ASnake programming language.
Author: Ahri Fox
License:                                  Apache License
Project-URL: Homepage, https://asnake.org
Project-URL: Github, https://github.com/AhriFoxSnek/ASnake
Project-URL: Issues, https://github.com/AhriFoxSnek/ASnake/issues
Keywords: programming language,transpiler,pyston,compiler
Classifier: Programming Language :: Python :: 3
Classifier: License :: OSI Approved :: Apache Software License
Classifier: Operating System :: OS Independent
Classifier: Operating System :: POSIX :: Linux
Classifier: Development Status :: 3 - Alpha
Classifier: Intended Audience :: Developers
Classifier: Natural Language :: English
Classifier: Programming Language :: Cython
Classifier: Programming Language :: Python :: Implementation :: CPython
Classifier: Programming Language :: Python :: Implementation :: MicroPython
Classifier: Programming Language :: Python :: Implementation :: PyPy
Classifier: Topic :: Software Development :: Code Generators
Classifier: Topic :: Software Development :: Version Control :: Git
Requires-Python: >=3.6
License-File: LICENSE.txt
Requires-Dist: sly>=0.4
Requires-Dist: autopep8>=1.5.5
Requires-Dist: ruff-api>=0.1.0
Dynamic: license-file
